sgfutil/__init__.py
sgfutil/lexer.py
sgfutil/parser.out
sgfutil/parser.py
sgfutil/parsetab.py
sgfutil/tree.py
sgfutil/__pycache__/__init__.cpython-38.pyc
sgfutil/__pycache__/lexer.cpython-38.pyc
sgfutil/__pycache__/parser.cpython-38.pyc
sgfutil/__pycache__/parsetab.cpython-38.pyc
sgfutil/__pycache__/sgfutil.cpython-38.pyc
sgfutil/__pycache__/tree.cpython-38.pyc
sgfutil-0.1.1.dist-info/LICENSE
sgfutil-0.1.1.dist-info/METADATA
sgfutil-0.1.1.dist-info/WHEEL
sgfutil-0.1.1.dist-info/top_level.txt
sgfutil-0.1.1.dist-info/RECORD
