Metadata-Version: 2.1
Name: sgfutil
Version: 0.1.1
Summary: An SGF utilization library for Go/chess game players.
Home-page: https://github.com/wklchris/python-sgfutil
Author: wklchris
Author-email: wklchris@hotmail.com
License: UNKNOWN
Platform: UNKNOWN
Classifier: Programming Language :: Python :: 3
Classifier: License :: OSI Approved :: MIT License
Classifier: Operating System :: OS Independent
Requires-Python: >=3.6
Requires-Dist: ply
